setup.cfg
setup.py
rbautofillbug/__init__.py
rbautofillbug/admin_urls.py
rbautofillbug/extension.py
rbautofillbug/forms.py
rbautofillbug.egg-info/PKG-INFO
rbautofillbug.egg-info/SOURCES.txt
rbautofillbug.egg-info/dependency_links.txt
rbautofillbug.egg-info/entry_points.txt
rbautofillbug.egg-info/not-zip-safe
rbautofillbug.egg-info/top_level.txt