Metadata-Version: 1.1
Name: rbautofillbug
Version: 0.1.3
Summary: A ReviewBoard extension that extracts bug IDs from review request summaries
Home-page: https://github.com/jjst/rbautofillbug
Author: Jeremie Jost
Author-email: jeremiejost@gmail.com
License: UNKNOWN
Download-URL: https://github.com/jjst/rbautofillbug/archive/v0.1.3.tar.gz
Keywords: reviewboard,extension
Platform: UNKNOWN
